akamaiossg/__init__.py
akamaiossg/config.py
akamaiossg/dictionary.py
akamaiossg/main.py
akamaiossg-1.0.0.dist-info/METADATA
akamaiossg-1.0.0.dist-info/WHEEL
akamaiossg-1.0.0.dist-info/top_level.txt
akamaiossg-1.0.0.dist-info/RECORD
